umetrix/__init__.py
umetrix/_version.py
umetrix/core.py
umetrix/notebooks.py
umetrix/render.py
umetrix-0.2.0.dist-info/LICENSE.md
umetrix-0.2.0.dist-info/METADATA
umetrix-0.2.0.dist-info/WHEEL
umetrix-0.2.0.dist-info/top_level.txt
umetrix-0.2.0.dist-info/RECORD
