Metadata-Version: 2.1
Name: umetrix
Version: 0.2.0
Summary: UNet Segmentation Metrics
Author-email: "Alan R. Lowe" <a.lowe@ucl.ac.uk>
License: BSD-3-Clause
Keywords: image analysis
Classifier: Programming Language :: Python :: 3
Requires-Python: >=3.8
License-File: LICENSE.md
Requires-Dist: matplotlib
Requires-Dist: numpy
Requires-Dist: pandas
Requires-Dist: scikit-learn
Requires-Dist: scikit-image >=0.20.0
